libtcd-0.1a1.dist-info/WHEEL
libtcd-0.1a1.dist-info/top_level.txt
libtcd-0.1a1.dist-info/DESCRIPTION.rst
libtcd-0.1a1.dist-info/metadata.json
libtcd-0.1a1.dist-info/METADATA
libtcd-0.1a1.dist-info/zip-safe
libtcd-0.1a1.dist-info/RECORD
libtcd/util.py
libtcd/__init__.py
libtcd/api.py
libtcd/_libtcd.py
libtcd/compat.py
libtcd/tests/test_api.py
libtcd/tests/__init__.py
libtcd/tests/test_util.py
libtcd/tests/test_compat.py
libtcd/tests/test_libtcd.py
libtcd/tests/test.tcd
