Metadata-Version: 2.0
Name: libtcd
Version: 0.1a1
Summary: Interface to xtide’s libtcd
Home-page: https://github.com/dairiki/python-libtcd
Author: Jeff Dairiki
Author-email: dairiki@dairiki.org
License: UNKNOWN
Keywords: xtide tides tidal currents
Platform: UNKNOWN
Classifier: Development Status :: 3 - Alpha
Classifier: Intended Audience :: Developers
Classifier: License :: OSI Approved :: BSD License
Classifier: Programming Language :: Python
Classifier: Programming Language :: Python :: 2.6
Classifier: Programming Language :: Python :: 2.7
Classifier: Programming Language :: Python :: 3.3
Classifier: Programming Language :: Python :: 3.4
Classifier: Programming Language :: Python :: Implementation :: CPython
Classifier: Topic :: Scientific/Engineering
Classifier: Topic :: Software Development :: Libraries
Requires-Dist: six
